{
  "Db.Meeting.Meeting.AttendeeList": "Список участников",
  "Db.Meeting.Meeting.EndDate": "Дата окончания",
  "Db.Meeting.Meeting.EntityPlural": "Встречи",
  "Db.Meeting.Meeting.EntitySingular": "Встреча",
  "Db.Meeting.Meeting.LocationId": "Код местанахождения",
  "Db.Meeting.Meeting.LocationName": "Местонахождение",
  "Db.Meeting.Meeting.MeetingGuid": "Guid встречи",
  "Db.Meeting.Meeting.MeetingId": "Код встречи",
  "Db.Meeting.Meeting.MeetingName": "Название встречи",
  "Db.Meeting.Meeting.MeetingNumber": "Количество встреч",
  "Db.Meeting.Meeting.MeetingTypeId": "Код типа встречи",
  "Db.Meeting.Meeting.MeetingTypeName": "Тип встречи",
  "Db.Meeting.Meeting.OrganizerContactEmail": "Email",
  "Db.Meeting.Meeting.OrganizerContactFirstName": "Имя",
  "Db.Meeting.Meeting.OrganizerContactFullName": "Полное имя",
  "Db.Meeting.Meeting.OrganizerContactId": "Код",
  "Db.Meeting.Meeting.OrganizerContactIdentityNo": "Номер",
  "Db.Meeting.Meeting.OrganizerContactLastName": "Фамилия",
  "Db.Meeting.Meeting.OrganizerContactTitle": "Заголовок",
  "Db.Meeting.Meeting.OrganizerContactUserId": "Код пользователя",
  "Db.Meeting.Meeting.ReporterContactEmail": "Email",
  "Db.Meeting.Meeting.ReporterContactFirstName": "Имя",
  "Db.Meeting.Meeting.ReporterContactFullName": "Полное имя",
  "Db.Meeting.Meeting.ReporterContactId": "Код",
  "Db.Meeting.Meeting.ReporterContactIdentityNo": "Номер",
  "Db.Meeting.Meeting.ReporterContactLastName": "Фамилия",
  "Db.Meeting.Meeting.ReporterContactTitle": "Заголовок",
  "Db.Meeting.Meeting.ReporterContactUserId": "Код пользователя",
  "Db.Meeting.Meeting.StartDate": "Дата начала",
  "Db.Meeting.Meeting.UnitId": "Код",
  "Db.Meeting.Meeting.UnitName": "Наименование",
  "Db.Meeting.Meeting.UnitParentUnitId": "Родитель",
  "Db.Meeting.MeetingAgenda.AgendaId": "Код",
  "Db.Meeting.MeetingAgenda.AgendaNumber": "Номер",
  "Db.Meeting.MeetingAgenda.AgendaTypeId": "Код типа задачи",
  "Db.Meeting.MeetingAgenda.AgendaTypeName": "Тип задачи",
  "Db.Meeting.MeetingAgenda.Attachments": "Вложения",
  "Db.Meeting.MeetingAgenda.Description": "Описание",
  "Db.Meeting.MeetingAgenda.EntityPlural": "Задачи",
  "Db.Meeting.MeetingAgenda.EntitySingular": "Задача",
  "Db.Meeting.MeetingAgenda.Images": "Изображения",
  "Db.Meeting.MeetingAgenda.MeetingEndDate": "Окончание встречи",
  "Db.Meeting.MeetingAgenda.MeetingId": "Код встречи",
  "Db.Meeting.MeetingAgenda.MeetingInsertDate": "Дата создания",
  "Db.Meeting.MeetingAgenda.MeetingInsertUserId": "Кем создана",
  "Db.Meeting.MeetingAgenda.MeetingLocationId": "Местонахождение",
  "Db.Meeting.MeetingAgenda.MeetingMeetingGuid": "Guid встречи",
  "Db.Meeting.MeetingAgenda.MeetingMeetingName": "Наименование",
  "Db.Meeting.MeetingAgenda.MeetingMeetingNumber": "Количество встреч",
  "Db.Meeting.MeetingAgenda.MeetingMeetingTypeId": "Код типа встречи",
  "Db.Meeting.MeetingAgenda.MeetingOrganizerContactId": "Организатор",
  "Db.Meeting.MeetingAgenda.MeetingReporterContactId": "Докладчик",
  "Db.Meeting.MeetingAgenda.MeetingStartDate": "Начало",
  "Db.Meeting.MeetingAgenda.MeetingUnitId": "Код единицы",
  "Db.Meeting.MeetingAgenda.MeetingUpdateDate": "Дата изменения",
  "Db.Meeting.MeetingAgenda.MeetingUpdateUserId": "Кем изменена",
  "Db.Meeting.MeetingAgenda.RequestedByContactEmail": "Email",
  "Db.Meeting.MeetingAgenda.RequestedByContactFirstName": "Имя",
  "Db.Meeting.MeetingAgenda.RequestedByContactFullName": "Полное имя",
  "Db.Meeting.MeetingAgenda.RequestedByContactId": "Код",
  "Db.Meeting.MeetingAgenda.RequestedByContactIdentityNo": "Номер",
  "Db.Meeting.MeetingAgenda.RequestedByContactLastName": "Фамилия",
  "Db.Meeting.MeetingAgenda.RequestedByContactTitle": "Заголовок",
  "Db.Meeting.MeetingAgenda.RequestedByContactUserId": "Код пользователя",
  "Db.Meeting.MeetingAgenda.Title": "Заголовок",
  "Db.Meeting.MeetingAgendaRelevant.AgendaAgendaNumber": "Количество",
  "Db.Meeting.MeetingAgendaRelevant.AgendaAgendaTypeId": "Тип",
  "Db.Meeting.MeetingAgendaRelevant.AgendaAttachments": "Вложения",
  "Db.Meeting.MeetingAgendaRelevant.AgendaDescription": "Описание",
  "Db.Meeting.MeetingAgendaRelevant.AgendaId": "Повестка дня",
  "Db.Meeting.MeetingAgendaRelevant.AgendaImages": "Изображения",
  "Db.Meeting.MeetingAgendaRelevant.AgendaMeetingId": "Код встречи",
  "Db.Meeting.MeetingAgendaRelevant.AgendaRelevantId": "Идентификатор",
  "Db.Meeting.MeetingAgendaRelevant.AgendaRequestedByContactId": "Кем запрошено",
  "Db.Meeting.MeetingAgendaRelevant.AgendaTitle": "Заголовок",
  "Db.Meeting.MeetingAgendaRelevant.ContactEmail": "Email",
  "Db.Meeting.MeetingAgendaRelevant.ContactFirstName": "Имя",
  "Db.Meeting.MeetingAgendaRelevant.ContactId": "Контакт",
  "Db.Meeting.MeetingAgendaRelevant.ContactIdentityNo": "Номер",
  "Db.Meeting.MeetingAgendaRelevant.ContactLastName": "Фамилия",
  "Db.Meeting.MeetingAgendaRelevant.ContactTitle": "Заголовок",
  "Db.Meeting.MeetingAgendaRelevant.ContactUserId": "Код пользователя",
  "Db.Meeting.MeetingAgendaRelevant.EntityPlural": "Повестка дня",
  "Db.Meeting.MeetingAgendaRelevant.EntitySingular": "Повестка дня",
  "Db.Meeting.MeetingAgendaType.AgendaTypeId": "Код задачи",
  "Db.Meeting.MeetingAgendaType.EntityPlural": "Типы задачи",
  "Db.Meeting.MeetingAgendaType.EntitySingular": "Тип задачи",
  "Db.Meeting.MeetingAgendaType.Name": "Название",
  "Db.Meeting.MeetingAttendee.AttendanceStatus": "Статус участников",
  "Db.Meeting.MeetingAttendee.AttendeeId": "Код задачи",
  "Db.Meeting.MeetingAttendee.AttendeeType": "Тип задачи",
  "Db.Meeting.MeetingAttendee.ContactEmail": "Email",
  "Db.Meeting.MeetingAttendee.ContactFirstName": "Имя",
  "Db.Meeting.MeetingAttendee.ContactFullName": "Полное имя",
  "Db.Meeting.MeetingAttendee.ContactId": "Код",
  "Db.Meeting.MeetingAttendee.ContactIdentityNo": "Номер",
  "Db.Meeting.MeetingAttendee.ContactLastName": "Фамилия",
  "Db.Meeting.MeetingAttendee.ContactTitle": "Заголовок",
  "Db.Meeting.MeetingAttendee.ContactUserId": "Код пользователя",
  "Db.Meeting.MeetingAttendee.EntityPlural": "Участники",
  "Db.Meeting.MeetingAttendee.EntitySingular": "Участники",
  "Db.Meeting.MeetingAttendee.MeetingEndDate": "Окончание встречи",
  "Db.Meeting.MeetingAttendee.MeetingId": "Код встречи",
  "Db.Meeting.MeetingAttendee.MeetingInsertDate": "Дата создания",
  "Db.Meeting.MeetingAttendee.MeetingInsertUserId": "Кем создан",
  "Db.Meeting.MeetingAttendee.MeetingLocationId": "Местонахождение",
  "Db.Meeting.MeetingAttendee.MeetingMeetingGuid": "Guid встречи",
  "Db.Meeting.MeetingAttendee.MeetingMeetingName": "Название встречи",
  "Db.Meeting.MeetingAttendee.MeetingMeetingNumber": "Количество",
  "Db.Meeting.MeetingAttendee.MeetingMeetingTypeId": "Код типа",
  "Db.Meeting.MeetingAttendee.MeetingOrganizerContactId": "Организатор",
  "Db.Meeting.MeetingAttendee.MeetingReporterContactId": "Выступающий",
  "Db.Meeting.MeetingAttendee.MeetingStartDate": "Начало",
  "Db.Meeting.MeetingAttendee.MeetingUnitId": "Код единицы",
  "Db.Meeting.MeetingAttendee.MeetingUpdateDate": "Изменено",
  "Db.Meeting.MeetingAttendee.MeetingUpdateUserId": "Кем изменено",
  "Db.Meeting.MeetingDecision.AgendaAgendaTypeId": "Код типа",
  "Db.Meeting.MeetingDecision.AgendaAttachments": "Вложения",
  "Db.Meeting.MeetingDecision.AgendaDescription": "Описание",
  "Db.Meeting.MeetingDecision.AgendaId": "Встреча",
  "Db.Meeting.MeetingDecision.AgendaImages": "Изображения",
  "Db.Meeting.MeetingDecision.AgendaMeetingId": "Код",
  "Db.Meeting.MeetingDecision.AgendaNumber": "Номер",
  "Db.Meeting.MeetingDecision.AgendaRequestedByContactId": "Кем запрошено",
  "Db.Meeting.MeetingDecision.AgendaTitle": "Заголовок",
  "Db.Meeting.MeetingDecision.Attachments": "Вложения",
  "Db.Meeting.MeetingDecision.DecisionId": "Код решения",
  "Db.Meeting.MeetingDecision.DecisionNumber": "Номер",
  "Db.Meeting.MeetingDecision.DecisionNumberName": "Название",
  "Db.Meeting.MeetingDecision.Description": "Описание",
  "Db.Meeting.MeetingDecision.DueDate": "Дата выполнения",
  "Db.Meeting.MeetingDecision.EntityPlural": "Решения",
  "Db.Meeting.MeetingDecision.EntitySingular": "Решение",
  "Db.Meeting.MeetingDecision.Images": "Изображения",
  "Db.Meeting.MeetingDecision.MeetingEndDate": "Окончание",
  "Db.Meeting.MeetingDecision.MeetingId": "Встреча",
  "Db.Meeting.MeetingDecision.MeetingInsertDate": "Дата создания",
  "Db.Meeting.MeetingDecision.MeetingInsertUserId": "Код пользователя",
  "Db.Meeting.MeetingDecision.MeetingLocationId": "Местонахождение",
  "Db.Meeting.MeetingDecision.MeetingMeetingGuid": "Guid встречи",
  "Db.Meeting.MeetingDecision.MeetingMeetingName": "Наименование",
  "Db.Meeting.MeetingDecision.MeetingMeetingNumber": "Количество",
  "Db.Meeting.MeetingDecision.MeetingMeetingTypeId": "Код типа",
  "Db.Meeting.MeetingDecision.MeetingOrganizerContactId": "Организатор",
  "Db.Meeting.MeetingDecision.MeetingReporterContactId": "Выступающий",
  "Db.Meeting.MeetingDecision.MeetingStartDate": "Начало",
  "Db.Meeting.MeetingDecision.MeetingUnitId": "Код единицы",
  "Db.Meeting.MeetingDecision.MeetingUpdateDate": "Дата изменения",
  "Db.Meeting.MeetingDecision.MeetingUpdateUserId": "Кем изменено",
  "Db.Meeting.MeetingDecision.ResolutionStatus": "Статус резолюции",
  "Db.Meeting.MeetingDecision.ResponsibleContactEmail": "Email",
  "Db.Meeting.MeetingDecision.ResponsibleContactFirstName": "Имя",
  "Db.Meeting.MeetingDecision.ResponsibleContactFullName": "Кем запрошено",
  "Db.Meeting.MeetingDecision.ResponsibleContactId": "Контакт",
  "Db.Meeting.MeetingDecision.ResponsibleContactIdentityNo": "Код",
  "Db.Meeting.MeetingDecision.ResponsibleContactLastName": "Фамилия",
  "Db.Meeting.MeetingDecision.ResponsibleContactTitle": "Заголовок",
  "Db.Meeting.MeetingDecision.ResponsibleContactUserId": "Код пользователя",
  "Db.Meeting.MeetingDecisionRelevant.ContactEmail": "Email",
  "Db.Meeting.MeetingDecisionRelevant.ContactFirstName": "Имя",
  "Db.Meeting.MeetingDecisionRelevant.ContactId": "Контакт",
  "Db.Meeting.MeetingDecisionRelevant.ContactIdentityNo": "Код",
  "Db.Meeting.MeetingDecisionRelevant.ContactLastName": "Фамилия",
  "Db.Meeting.MeetingDecisionRelevant.ContactTitle": "Заголовок",
  "Db.Meeting.MeetingDecisionRelevant.ContactUserId": "Код пользователя",
  "Db.Meeting.MeetingDecisionRelevant.DecisionAgendaId": "Задача",
  "Db.Meeting.MeetingDecisionRelevant.DecisionAttachments": "Вложения",
  "Db.Meeting.MeetingDecisionRelevant.DecisionDecisionNumber": "Количество",
  "Db.Meeting.MeetingDecisionRelevant.DecisionDescription": "Описание",
  "Db.Meeting.MeetingDecisionRelevant.DecisionDueDate": "Дата выполнения",
  "Db.Meeting.MeetingDecisionRelevant.DecisionId": "Код решения",
  "Db.Meeting.MeetingDecisionRelevant.DecisionImages": "Изображения",
  "Db.Meeting.MeetingDecisionRelevant.DecisionMeetingId": "Код встречи",
  "Db.Meeting.MeetingDecisionRelevant.DecisionRelevantId": "Код соответствия",
  "Db.Meeting.MeetingDecisionRelevant.DecisionResolutionStatus": "Статус резолюции",
  "Db.Meeting.MeetingDecisionRelevant.DecisionResponsibleContactId": "Контакт",
  "Db.Meeting.MeetingDecisionRelevant.EntityPlural": "Решения организатора",
  "Db.Meeting.MeetingDecisionRelevant.EntitySingular": "Решение организатора",
  "Db.Meeting.MeetingLocation.Address": "Адрес",
  "Db.Meeting.MeetingLocation.EntityPlural": "Местоположения",
  "Db.Meeting.MeetingLocation.EntitySingular": "Местоположение",
  "Db.Meeting.MeetingLocation.Latitude": "Широта",
  "Db.Meeting.MeetingLocation.LocationId": "Код местоположения",
  "Db.Meeting.MeetingLocation.Longitude": "Долгота",
  "Db.Meeting.MeetingLocation.Name": "Название",
  "Db.Meeting.MeetingType.EntityPlural": "Типы",
  "Db.Meeting.MeetingType.EntitySingular": "Тип",
  "Db.Meeting.MeetingType.MeetingTypeId": "Код типа",
  "Db.Meeting.MeetingType.Name": "Название",
  "Enums.Meeting.MeetingAttendanceStatus.Absent": "Отсутствующие",
  "Enums.Meeting.MeetingAttendanceStatus.AbsentWithPermission": "Отсутствующие c разрешения",
  "Enums.Meeting.MeetingAttendanceStatus.Attended": "Присутствующие",
  "Enums.Meeting.MeetingAttendanceStatus.NotSet": "Не установлено",
  "Enums.Meeting.MeetingAttendeeType.Attendee": "Слушатели",
  "Enums.Meeting.MeetingAttendeeType.Guest": "Гости",
  "Navigation.Meeting": "Встреча",
  "Navigation.Meeting/Meeting Agenda Types": "Типы повестки дня",
  "Navigation.Meeting/Meeting Locations": "Местоположение",
  "Navigation.Meeting/Meeting Types": "Типы встреч",
  "Navigation.Meeting/Meetings": "Встречи"
}